llama_index/readers/feedly_rss/__init__.py
llama_index/readers/feedly_rss/base.py
llama_index_readers_feedly_rss-0.4.1.dist-info/METADATA
llama_index_readers_feedly_rss-0.4.1.dist-info/WHEEL
llama_index_readers_feedly_rss-0.4.1.dist-info/licenses/LICENSE
llama_index_readers_feedly_rss-0.4.1.dist-info/RECORD
