Metadata-Version: 2.4
Name: llama-index-readers-feedly-rss
Version: 0.4.1
Summary: llama-index readers feedly_rss integration
Author-email: Your Name <you@example.com>
Maintainer: kychanbp
License-Expression: MIT
License-File: LICENSE
Keywords: feedly,rss
Requires-Python: <4.0,>=3.9
Requires-Dist: feedly-client<0.27,>=0.26
Requires-Dist: llama-index-core<0.15,>=0.13.0
